fajita/__init__.py
fajita/client.py
fajita/cookie_repository.py
fajita/fajita.py
fajita-0.0.2.dist-info/LICENSE
fajita-0.0.2.dist-info/METADATA
fajita-0.0.2.dist-info/WHEEL
fajita-0.0.2.dist-info/top_level.txt
fajita-0.0.2.dist-info/RECORD
